gitsummary/__init__.py
gitsummary/gitsummary.py
gitsummary-0.2.dist-info/LICENSE.txt
gitsummary-0.2.dist-info/METADATA
gitsummary-0.2.dist-info/WHEEL
gitsummary-0.2.dist-info/top_level.txt
gitsummary-0.2.dist-info/RECORD
