Metadata-Version: 2.1
Name: gitsummary
Version: 0.2
Summary: print a one-line summary of the current git repository, the current branch, and the hash for the current branch head
Home-page: https://github.com/Timothy-W-Hilton/gitsummary
Project-URL: Bug Tracker, https://github.com/Timothy-W-Hilton/gitsummary/issues
Classifier: Programming Language :: Python :: 3
Classifier: License :: OSI Approved :: MIT License
Classifier: Operating System :: OS Independent
Requires-Python: >=3.8
License-File: LICENSE.txt
Requires-Dist: GitPython
